[
  {
    "rank": 1,
    "program_name": "Acme Cyber SaaS",
    "verticals": ["cybersecurity","saas"],
    "payout_model": "recurring",
    "typical_payout_range": "$200–$1500",
    "regions": ["US","EU","UK","APAC"],
    "automation_score": 5,
    "api_ready": true,
    "conversion_reporting": {"type":"api","docs_url":"https://docs.example.com/acme"},
    "deep_link_template": "https://acme.example.com/?aff={AFF_ID}&s1={CLICK_ID}&dest={URLENCODED_DEST}",
    "source_url": "https://acme.example.com/partners",
    "payout_rank": 9
  },
  {
    "rank": 2,
    "program_name": "Zen Data Feeds",
    "verticals": ["data_feeds","analytics"],
    "payout_model": "recurring",
    "typical_payout_range": "$120–$900",
    "regions": ["US","EU","UK"],
    "automation_score": 4,
    "api_ready": true,
    "conversion_reporting": {"type":"postback"},
    "deep_link_template": "https://zen.example.com/?ref={AFF_ID}&cid={CLICK_ID}&u={URLENCODED_DEST}",
    "source_url": "https://zen.example.com/partners",
    "payout_rank": 8
  },
  {
    "rank": 3,
    "program_name": "Nimbus Docs AI",
    "verticals": ["productivity","ai_copilot"],
    "payout_model": "bounty+recurring",
    "typical_payout_range": "$50–$600",
    "regions": ["US","EU","UK","APAC"],
    "automation_score": 4,
    "api_ready": true,
    "conversion_reporting": {"type":"api"},
    "deep_link_template": "https://nimbus.example.com/?a={AFF_ID}&c={CLICK_ID}&d={URLENCODED_DEST}",
    "source_url": "https://nimbus.example.com/affiliates",
    "payout_rank": 7
  },
  {
    "rank": 4,
    "program_name": "Atlas Finance Suite",
    "verticals": ["b2b_finance_tools"],
    "payout_model": "recurring",
    "typical_payout_range": "$150–$1000",
    "regions": ["US","EU","UK"],
    "automation_score": 5,
    "api_ready": true,
    "conversion_reporting": {"type":"postback"},
    "deep_link_template": "https://atlas.example.com/?ref={AFF_ID}&s1={CLICK_ID}&dest={URLENCODED_DEST}",
    "source_url": "https://atlas.example.com/partners",
    "payout_rank": 8
  },
  {
    "rank": 5,
    "program_name": "LedgerCloud ERP",
    "verticals": ["erp","accounting"],
    "payout_model": "recurring",
    "typical_payout_range": "$100–$750",
    "regions": ["US","EU","UK","APAC"],
    "automation_score": 4,
    "api_ready": true,
    "conversion_reporting": {"type":"api"},
    "deep_link_template": "https://ledgercloud.example.com/?affid={AFF_ID}&cid={CLICK_ID}&to={URLENCODED_DEST}",
    "source_url": "https://ledgercloud.example.com/affiliates",
    "payout_rank": 7
  },
  {
    "rank": 6,
    "program_name": "Semi-Auto RPA",
    "verticals": ["automation","rpa"],
    "payout_model": "recurring",
    "typical_payout_range": "$80–$500",
    "regions": ["US","EU","UK"],
    "automation_score": 5,
    "api_ready": true,
    "conversion_reporting": {"type":"api"},
    "deep_link_template": "https://rpa.example.com/?a={AFF_ID}&c={CLICK_ID}&u={URLENCODED_DEST}",
    "source_url": "https://rpa.example.com/partners",
    "payout_rank": 6
  },
  {
    "rank": 7,
    "program_name": "SignalMail B2B",
    "verticals": ["email","marketing_automation"],
    "payout_model": "recurring",
    "typical_payout_range": "$60–$400",
    "regions": ["US","EU","UK","APAC"],
    "automation_score": 4,
    "api_ready": true,
    "conversion_reporting": {"type":"postback"},
    "deep_link_template": "https://signalmail.example.com/?ref={AFF_ID}&cid={CLICK_ID}&dest={URLENCODED_DEST}",
    "source_url": "https://signalmail.example.com/partners",
    "payout_rank": 6
  },
  {
    "rank": 8,
    "program_name": "GuardStack IAM",
    "verticals": ["cybersecurity","identity"],
    "payout_model": "bounty+recurring",
    "typical_payout_range": "$100–$900",
    "regions": ["US","EU","UK"],
    "automation_score": 4,
    "api_ready": true,
    "conversion_reporting": {"type":"api"},
    "deep_link_template": "https://guard.example.com/?aff={AFF_ID}&s1={CLICK_ID}&goto={URLENCODED_DEST}",
    "source_url": "https://guard.example.com/partners",
    "payout_rank": 7
  },
  {
    "rank": 9,
    "program_name": "Vector BI Cloud",
    "verticals": ["analytics","bi"],
    "payout_model": "recurring",
    "typical_payout_range": "$80–$650",
    "regions": ["US","EU","UK","APAC"],
    "automation_score": 4,
    "api_ready": true,
    "conversion_reporting": {"type":"api"},
    "deep_link_template": "https://vector.example.com/?a={AFF_ID}&c={CLICK_ID}&d={URLENCODED_DEST}",
    "source_url": "https://vector.example.com/affiliates",
    "payout_rank": 6
  },
  {
    "rank": 10,
    "program_name": "FlowDesk Project",
    "verticals": ["productivity","project_mgmt"],
    "payout_model": "recurring",
    "typical_payout_range": "$50–$300",
    "regions": ["US","EU","UK","APAC"],
    "automation_score": 3,
    "api_ready": true,
    "conversion_reporting": {"type":"postback"},
    "deep_link_template": "https://flowdesk.example.com/?ref={AFF_ID}&cid={CLICK_ID}&u={URLENCODED_DEST}",
    "source_url": "https://flowdesk.example.com/partners",
    "payout_rank": 5
  },
  {
    "rank": 11,
    "program_name": "BridgeForms eSign",
    "verticals": ["legaltech","productivity"],
    "payout_model": "recurring",
    "typical_payout_range": "$60–$450",
    "regions": ["US","EU","UK"],
    "automation_score": 4,
    "api_ready": true,
    "conversion_reporting": {"type":"api"},
    "deep_link_template": "https://bridgeforms.example.com/?a={AFF_ID}&c={CLICK_ID}&to={URLENCODED_DEST}",
    "source_url": "https://bridgeforms.example.com/affiliates",
    "payout_rank": 6
  },
  {
    "rank": 12,
    "program_name": "StackOps DevTools",
    "verticals": ["devtools","observability"],
    "payout_model": "recurring",
    "typical_payout_range": "$70–$500",
    "regions": ["US","EU","UK","APAC"],
    "automation_score": 4,
    "api_ready": true,
    "conversion_reporting": {"type":"api"},
    "deep_link_template": "https://stackops.example.com/?aff={AFF_ID}&s1={CLICK_ID}&dest={URLENCODED_DEST}",
    "source_url": "https://stackops.example.com/partners",
    "payout_rank": 6
  }
]
